docker_swarm_plugin/__init__.py
docker_swarm_plugin/main.py
docker_swarm_plugin/models/__init__.py
docker_swarm_plugin/services/__init__.py
docker_swarm_plugin/services/cluster_config_service.py
docker_swarm_plugin-1.0.0.dist-info/METADATA
docker_swarm_plugin-1.0.0.dist-info/WHEEL
docker_swarm_plugin-1.0.0.dist-info/top_level.txt
docker_swarm_plugin-1.0.0.dist-info/RECORD
