Metadata-Version: 2.1
Name: docker_swarm_plugin
Version: 1.0.0
Summary: An AmbientEdgeServer plugin for managing docker swarms
Author-email: Jose Catarino <jose@ambientlabscomputing.com>
License: MIT
Requires-Python: >=3.7
Requires-Dist: pydantic <=2.7.4
Requires-Dist: ambient-backend-api-client <=0.9.0
